rabbitmqX/__init__.py
rabbitmqX/command/__init__.py
rabbitmqX/command/command.py
rabbitmqX/journal/__init__.py
rabbitmqX/journal/journal.py
rabbitmqX/patterns/__init__.py
rabbitmqX/patterns/client/__init__.py
rabbitmqX/patterns/client/rpc_client.py
rabbitmqX/patterns/client/topic_client.py
rabbitmqX/patterns/client/work_queue_task_client.py
rabbitmqX/patterns/server/__init__.py
rabbitmqX/patterns/server/rpc_server.py
rabbitmqX/patterns/server/topic_server.py
rabbitmqX/patterns/server/work_queue_task_server.py
rabbitmqX-1.10.19.dist-info/LICENSE
rabbitmqX-1.10.19.dist-info/METADATA
rabbitmqX-1.10.19.dist-info/WHEEL
rabbitmqX-1.10.19.dist-info/top_level.txt
rabbitmqX-1.10.19.dist-info/RECORD
