Metadata-Version: 2.1
Name: rabbitmqX
Version: 1.10.19
Summary: Implementation RabbitMQ's Design Patterns 
Home-page: UNKNOWN
Author: Paulo Sergio dos Santo Junior
Author-email: paulossjuniort@gmail.com
License: UNKNOWN
Platform: UNKNOWN
Classifier: Programming Language :: Python :: 3
Classifier: License :: OSI Approved :: MIT License
Classifier: Operating System :: OS Independent
Requires-Dist: pika
